{
  "inspection_id": "INS_20260610_192235_008",
  "timestamp": "2026-06-10T19:22:35Z",
  "image_path": "data/images/ambiguous/train_1346.jpg",
  "zone_id": "Z_CMP",
  "overall_status": "ok",
  "issues": [],
  "shelf_fill_rate": 0.95,
  "products_detected": [
    "shampoo",
    "condicionador",
    "laquê",
    "spray de cabelo",
    "gel de cabelo",
    "creme de cabelo",
    "loção corporal"
  ],
  "model_reasoning": "A prateleira está bem abastecida com uma variedade de produtos de cuidados capilares e corporais. Não foram detetados problemas significativos como prateleiras vazias, produtos errados, danificados, desalinhados ou etiquetas em falta. A taxa de preenchimento da prateleira é alta.",
  "_strategy": "A",
  "_from_cache": true
}